restfx/__init__.py
restfx/__meta__.py
restfx/app.py
restfx/config.py
restfx/globs.py
restfx/commands/__init__.py
restfx/commands/commands.py
restfx/http/__init__.py
restfx/http/request.py
restfx/http/response.py
restfx/internal_assets/sample.tar.gz
restfx/internal_assets/scripts/base64.js
restfx/internal_assets/scripts/enums.js
restfx/internal_assets/scripts/export.js
restfx/internal_assets/scripts/index.js
restfx/internal_assets/scripts/jsonviewer.js
restfx/internal_assets/scripts/navigation.js
restfx/internal_assets/scripts/options.js
restfx/internal_assets/scripts/panel.js
restfx/internal_assets/scripts/renderers.js
restfx/internal_assets/scripts/search.js
restfx/internal_assets/scripts/taboverride.min.js
restfx/internal_assets/scripts/test.js
restfx/internal_assets/scripts/xhr.js
restfx/internal_assets/scripts/zepto.min.js
restfx/internal_assets/styles/apis.css
restfx/internal_assets/styles/common.css
restfx/internal_assets/styles/enums.css
restfx/internal_assets/styles/jsonviewer.css
restfx/internal_assets/styles/layout.css
restfx/internal_assets/styles/navigation.css
restfx/internal_assets/styles/options.css
restfx/internal_assets/styles/panel.css
restfx/internal_assets/styles/search.css
restfx/internal_assets/styles/tabs.css
restfx/internal_assets/styles/test.css
restfx/internal_assets/styles/x-ie.css
restfx/internal_assets/templates/api_page.html
restfx/middleware/__init__.py
restfx/middleware/access.py
restfx/middleware/interface.py
restfx/middleware/manager.py
restfx/middleware/methods.py
restfx/middleware/middlewares/__init__.py
restfx/middleware/middlewares/auth.py
restfx/middleware/middlewares/check_referer.py
restfx/middleware/middlewares/options.py
restfx/middleware/middlewares/session.py
restfx/middleware/middlewares/timetick.py
restfx/plugin/__init__.py
restfx/plugin/interface.py
restfx/routes/__init__.py
restfx/routes/api_page.py
restfx/routes/collector.py
restfx/routes/decorator.py
restfx/routes/meta.py
restfx/routes/parameter_interface.py
restfx-0.32.0.dist-info/LICENSE
restfx-0.32.0.dist-info/LICENSE.WERKZEUG.rst
restfx-0.32.0.dist-info/METADATA
restfx-0.32.0.dist-info/WHEEL
restfx-0.32.0.dist-info/entry_points.txt
restfx-0.32.0.dist-info/top_level.txt
restfx-0.32.0.dist-info/RECORD
