Metadata-Version: 2.1
Name: restfx
Version: 0.32.0
Summary: A RESTful framework for Python3.
Home-page: https://gitee.com/wangankeji-fe/restfx
Author: hyjiacan
Author-email: hyjiacan@163.com
Maintainer: hyjiacan
Maintainer-email: hyjiacan@163.com
License: UNKNOWN
Project-URL: Documentation, https://gitee.com/wangankeji-fe/restfx/wikis
Project-URL: Repository, https://gitee.com/wangankeji-fe/restfx
Project-URL: Issue tracker, https://gitee.com/wangankeji-fe/restfx/issues
Platform: UNKNOWN
Classifier: Development Status :: 4 - Beta
Classifier: Environment :: Web Environment
Classifier: Intended Audience :: Developers
Classifier: License :: OSI Approved :: MIT License
Classifier: Operating System :: OS Independent
Classifier: Programming Language :: Python :: 3
Classifier: Topic :: Internet :: WWW/HTTP :: Dynamic Content
Classifier: Topic :: Internet :: WWW/HTTP :: WSGI
Classifier: Topic :: Internet :: WWW/HTTP :: WSGI :: Application
Classifier: Topic :: Software Development :: Libraries :: Application Frameworks
Requires-Python: >=3.6
Requires-Dist: Werkzeug (>=2.0.3)
